holistic/__about__.py
holistic/__init__.py
holistic/bias/metrics/__init__.py
holistic/bias/metrics/_classification.py
holistic/bias/metrics/_clustering.py
holistic/bias/metrics/_multiclass.py
holistic/bias/metrics/_recommender.py
holistic/bias/metrics/_regression.py
holistic/bias/mitigation/__init__.py
holistic/bias/mitigation/commons/disparate_impact_remover/__init__.py
holistic/bias/mitigation/commons/disparate_impact_remover/_categorical_feature.py
holistic/bias/mitigation/commons/disparate_impact_remover/_categorical_repairer.py
holistic/bias/mitigation/commons/disparate_impact_remover/_numerical_repairer.py
holistic/bias/mitigation/commons/disparate_impact_remover/_sparse_list.py
holistic/bias/mitigation/commons/disparate_impact_remover/_utils.py
holistic/bias/mitigation/commons/fairlet_clustering/__init__.py
holistic/bias/mitigation/commons/fairlet_clustering/_utils.py
holistic/bias/mitigation/commons/fairlet_clustering/clustering/__init__.py
holistic/bias/mitigation/commons/fairlet_clustering/clustering/_kcenters.py
holistic/bias/mitigation/commons/fairlet_clustering/clustering/_kmedoids.py
holistic/bias/mitigation/commons/fairlet_clustering/decomposition/__init__.py
holistic/bias/mitigation/commons/fairlet_clustering/decomposition/_base.py
holistic/bias/mitigation/commons/fairlet_clustering/decomposition/_scalable.py
holistic/bias/mitigation/commons/fairlet_clustering/decomposition/_vanilla.py
holistic/bias/mitigation/commons/fairlet_clustering/decompositions/__init__.py
holistic/bias/mitigation/commons/fairlet_clustering/decompositions/_base.py
holistic/bias/mitigation/commons/fairlet_clustering/decompositions/_scalable.py
holistic/bias/mitigation/commons/fairlet_clustering/decompositions/_vanilla.py
holistic/bias/mitigation/inprocessing/__init__.py
holistic/bias/mitigation/inprocessing/adversarial_debiasing/__init__.py
holistic/bias/mitigation/inprocessing/adversarial_debiasing/models.py
holistic-1.0.10.dist-info/METADATA
holistic-1.0.10.dist-info/WHEEL
holistic-1.0.10.dist-info/licenses/LICENSE
holistic-1.0.10.dist-info/RECORD
