Metadata-Version: 2.3
Name: holistic
Version: 1.0.10
Project-URL: Documentation, https://github.com/holistic-ai/holisticai#readme
Project-URL: Issues, https://github.com/holistic-ai/holisticai/issues
Project-URL: Source, https://github.com/holistic-ai/holisticai
Author-email: research <research@holisticai.com>
License-Expression: MIT
License-File: LICENSE
Classifier: Development Status :: 4 - Beta
Classifier: Programming Language :: Python
Classifier: Programming Language :: Python :: 3.8
Classifier: Programming Language :: Python :: 3.9
Classifier: Programming Language :: Python :: 3.10
Classifier: Programming Language :: Python :: 3.11
Classifier: Programming Language :: Python :: 3.12
Classifier: Programming Language :: Python :: Implementation :: CPython
Classifier: Programming Language :: Python :: Implementation :: PyPy
Requires-Python: >=3.8
Requires-Dist: dill==0.3.6
Requires-Dist: pandas
Requires-Dist: pyarrow
Requires-Dist: requests==2.31.0
Provides-Extra: all
Requires-Dist: flax>=0.8.5; extra == 'all'
Requires-Dist: jax>=0.4.30; extra == 'all'
Requires-Dist: lime>=0.2.0.1; extra == 'all'
Requires-Dist: networkx>=3.1; extra == 'all'
Requires-Dist: optax>=0.2.3; extra == 'all'
Requires-Dist: pygad==3.3.1; extra == 'all'
Requires-Dist: shap>=0.42.1; extra == 'all'
Provides-Extra: bias
Requires-Dist: flax>=0.8.5; extra == 'bias'
Requires-Dist: jax>=0.4.30; extra == 'bias'
Requires-Dist: matplotlib; extra == 'bias'
Requires-Dist: numpy>=1.25; extra == 'bias'
Requires-Dist: optax>=0.2.3; extra == 'bias'
Requires-Dist: pandas; extra == 'bias'
Requires-Dist: pygad==3.3.1; extra == 'bias'
Requires-Dist: scikit-learn>=1.0.2; extra == 'bias'
Requires-Dist: seaborn; extra == 'bias'
Provides-Extra: explainability
Requires-Dist: lime>=0.2.0.1; extra == 'explainability'
Requires-Dist: shap>=0.42.1; extra == 'explainability'
Provides-Extra: security
Requires-Dist: jax>=0.4.30; extra == 'security'
